<mujocoinclude>
    <actuator>
        <general biasprm="0.381903 1.46199 604.625 1 0.0669801 2.99607 10 1.34206 1.4 0" class="muscle" gainprm="631.360531044 0.097193502152 0.0348080472906 10.000000001 0.567054318052 -1.75468309422 1.50000000015 5.0000000005 0.037517457159" lengthrange="0.0748245 0.186181" name="addbrev_r" tendon="addbrev_r_tendon" gaintype="compliant_mtu" />
        <general biasprm="0.361607 1.56839 881.938 1 0.126715 3.5 10 1.50984 1.4 0" class="muscle" gainprm="916.800496497 0.108042356079 0.131738967184 10.000000001 0.559915042633 -2.99538355964 1.50000000015 5.0000000005 0.0399919616931" lengthrange="0.170925 0.301499" name="addlong_r" tendon="addlong_r_tendon" gaintype="compliant_mtu" />
        <general biasprm="0.647072 1.32551 576.186 1 0.000543367 2.1578 10 1.60782 1.4 0" class="muscle" gainprm="556.161980009 0.165223108449 0.0859723648428 10.000000052 0.682471608034 -2.51439918445 1.50000005155 5.00000005172 0.036546794918" lengthrange="0.202042 0.322261" name="addmagDist_r" tendon="addmagDist_r_tendon" gaintype="compliant_mtu" />
        <general biasprm="0.662907 1.54717 564.689 1 0.132471 3.5 10 1.6643 1.4 0" class="muscle" gainprm="560.113678756 0.13742241467 0.205725823411 10.0000000995 0.682123083771 -2.84154704207 1.5000000995 5.0000000995 0.132859400081" lengthrange="0.319889 0.458011" name="addmagIsch_r" tendon="addmagIsch_r_tendon" gaintype="compliant_mtu" />
        <general biasprm="0.477896 1.27927 577.178 1 0.0269359 2.05759 10 1.69396 1.4 0" class="muscle" gainprm="555.695452119 0.127774760301 0.0458046062033 10.0000000006 0.684228487441 -2.52165537951 1.50000000009 5.00000000029 0.0363339286248" lengthrange="0.112434 0.222784" name="addmagMid_r" tendon="addmagMid_r_tendon" gaintype="compliant_mtu" />
        <general biasprm="0.1628 1.1024 575.376 1 0 1.50093 10 1.38182 1.4 0" class="muscle" gainprm="542.213173705 0.089760565717 0.0383224967735 10.0000000454 0.74061126063 -2.58233859967 1.50000004497 5.00000004516 0.206138261913" lengthrange="0.0575158 0.156738" name="addmagProx_r" tendon="addmagProx_r_tendon" gaintype="compliant_mtu" />
        <general biasprm="0.1 1.8 1328.94 1 0.05 3.5 10 1.98303 1.4 0" class="muscle" gainprm="1230.45123603 0.087424245875 0.320979149479 10.0000001 0.732585198375 -3.85239006352 1.5000001 5.0000001 0.0911562254984" lengthrange="0.311093 0.518283" name="bflh_r" tendon="bflh_r_tendon" gaintype="compliant_mtu" />
        <general biasprm="0.406318 1.19782 586.382 1 0 1.59685 10 1.58092 1.4 0" class="muscle" gainprm="506.27055531 0.0937556165498 0.100527108051 10.0000001 0.732685732362 -2.8530150457 1.5000001 5.0000001 0.157323783368" lengthrange="0.150634 0.237936" name="bfsh_r" tendon="bfsh_r_tendon" gaintype="compliant_mtu" />
        <general biasprm="0.620259 1.40474 553.241 1 0.319949 3.12081 10 1.35486 1.4 0" class="muscle" gainprm="559.614385207 0.0617745094574 0.357547003967 10.0000000005 0.730624602016 -3.58420125982 1.5000000005 5.0000000005 0.0854096547223" lengthrange="0.411859 0.466224" name="edl_r" tendon="edl_r_tendon" gaintype="compliant_mtu" />
        <general biasprm="0.696496 1.41065 265.537 1 0.344704 3.25853 10 1.48683 1.4 0" class="muscle" gainprm="265.844496682 0.067987168893 0.316808734368 10.0000000995 0.713538551072 -3.43849524084 1.5000000995 5.0000000995 0.0818235539232" lengthrange="0.378893 0.432312" name="ehl_r" tendon="ehl_r_tendon" gaintype="compliant_mtu" />
        <general biasprm="0.598501 1.22918 332.13 1 0.357129 3.24643 10 1.8954 1.4 0" class="muscle" gainprm="391.882926639 0.0402059383655 0.371415046347 10.0000001 0.676348245751 -2.73102756238 1.5000001 5.0000001 0.0687195816217" lengthrange="0.405466 0.433594" name="fdl_r" tendon="fdl_r_tendon" gaintype="compliant_mtu" />
        <general biasprm="0.562474 1.18745 749.779 1 0.292699 2.98554 10 1.03099 1.4 0" class="muscle" gainprm="832.577258483 0.0487431918584 0.343592607774 10 0.669825002137 -2.76552576086 1.5 5 0.0779805938534" lengthrange="0.383982 0.416918" name="fhl_r" tendon="fhl_r_tendon" gaintype="compliant_mtu" />
        <general biasprm="0.1 1.49069 1318.66 1 0.05 3.5 10 1.90363 1.4 0" class="muscle" gainprm="1516.19818422 0.0675881325746 0.369999699057 10 0.62795302995 -1.55140593381 1.5 5 0.0610440482055" lengthrange="0.366291 0.463723" name="gaslat_r" tendon="gaslat_r_tendon" gaintype="compliant_mtu" />
        <general biasprm="0.1 1.45 2237.29 1 0.0989568 3.5 10 1.51773 1.4 0" class="muscle" gainprm="2852.5615188 0.0574614775061 0.384356120709 10.0000000516 0.596452113604 -2.42165751997 1.50000005116 5.00000005133 0.0394390444885" lengthrange="0.371968 0.472667" name="gasmed_r" tendon="gasmed_r_tendon" gaintype="compliant_mtu" />
        <general biasprm="0.680894 1.34594 1293.79 1 0 1.99579 10 1.86621 1.4 0" class="muscle" gainprm="859.41192231 0.124950024379 0.0829350003361 10.0000000076 0.739059147845 -2.29745652698 1.5000000076 5.0000000076 0.162582312842" lengthrange="0.148932 0.246694" name="glmax1_r" tendon="glmax1_r_tendon" gaintype="compliant_mtu" />
        <general biasprm="0.684001 1.42041 1308.46 1 0 3.44601 10 1.22459 1.4 0" class="muscle" gainprm="1213.38892283 0.133878707032 0.103738915445 10.000000063 0.737550549812 -2.24193529383 1.50000006295 5.00000006299 0.137254076028" lengthrange="0.175275 0.290891" name="glmax2_r" tendon="glmax2_r_tendon" gaintype="compliant_mtu" />
        <general biasprm="1.36664 1.8 928.184 1 0.824721 3.5 10 1.37074 1.4 0" class="muscle" gainprm="812.119706011 0.141950052364 0.0978628790291 10.0000000578 0.754487995245 -2.39823389798 1.50000005779 5.00000005779 0.130815916507" lengthrange="0.297946 0.474778" name="glmax3_r" tendon="glmax3_r_tendon" gaintype="compliant_mtu" />
        <general biasprm="0.103084 1.4555 1018.46 1 0 3.49286 10 1.55125 1.4 0" class="muscle" gainprm="973.355928205 0.0650250091274 0.055575000039 10 0.730599854042 -2.432496862 1.5 5 0.162629781677" lengthrange="0.063342 0.162068" name="glmed1_r" tendon="glmed1_r_tendon" gaintype="compliant_mtu" />
        <general biasprm="0.147694 1.46079 715.019 1 0 3.5 10 1.62169 1.4 0" class="muscle" gainprm="698.127045045 0.0714320564733 0.0736093643994 10.0000000395 0.705261787181 -1.84479407161 1.50000003948 5.00000003948 0.167207243316" lengthrange="0.0760304 0.171887" name="glmed2_r" tendon="glmed2_r_tendon" gaintype="compliant_mtu" />
        <general biasprm="0.125877 1.51901 828.084 1 0 3.5 10 1.38543 1.4 0" class="muscle" gainprm="812.15087769 0.0664156946279 0.0470613845276 10.0000000487 0.668720871356 -1.53426422178 1.50000004869 5.00000004869 0.239571795188" lengthrange="0.0544219 0.156121" name="glmed3_r" tendon="glmed3_r_tendon" gaintype="compliant_mtu" />
        <general biasprm="0.1 1.44635 357.161 1 0.0576443 3.07057 10 1.2057 1.4 0" class="muscle" gainprm="350.282106104 0.0758592248494 0.0190059710581 10 0.678571299824 -2.52755874365 1.5 5 0.0363773490968" lengthrange="0.0229136 0.11449" name="glmin1_r" tendon="glmin1_r_tendon" gaintype="compliant_mtu" />
        <general biasprm="0.1 1.60052 392.017 1 0.05 3.5 10 1.20071 1.4 0" class="muscle" gainprm="374.169384518 0.0646083117723 0.0316051917777 10.0000000324 0.66701794083 -2.65673818037 1.50000003184 5.00000003208 0.0369183080949" lengthrange="0.0298796 0.115728" name="glmin2_r" tendon="glmin2_r_tendon" gaintype="compliant_mtu" />
        <general biasprm="0.1 1.8 386.063 1 0.0906571 3.5 10 1.40703 1.4 0" class="muscle" gainprm="426.354064508 0.0315612898765 0.0461500888966 10.0000000995 0.661510841193 -2.66543882264 1.5000000995 5.0000000995 0.10281777196" lengthrange="0.0345943 0.11994" name="glmin3_r" tendon="glmin3_r_tendon" gaintype="compliant_mtu" />
        <general biasprm="0.652458 1.62414 280.917 1 0.00265608 3.5 10 0.938556 1.4 0" class="muscle" gainprm="272.783280789 0.200310838306 0.166346137838 10.0000000995 0.673032658858 -2.21286958079 1.5000000995 5.0000000995 0.196976636585" lengthrange="0.320644 0.541993" name="grac_r" tendon="grac_r_tendon" gaintype="compliant_mtu" />
        <general biasprm="0.24456 1.23695 977.408 1 0.0058227 1.83512 10 1.82107 1.4 0" class="muscle" gainprm="1023.22974197 0.110522663509 0.0996167649857 10 0.475237427473 -0.454363166869 1.5 5 0.0622475705423" lengthrange="0.122191 0.22798" name="iliacus_r" tendon="iliacus_r_tendon" gaintype="compliant_mtu" />
        <general biasprm="0.845027 1.32175 496.045 1 0.461019 3.09903 10 1.80009 1.4 0" class="muscle" gainprm="485.49059667 0.0411863690606 0.14264109552 10.0000000995 0.667285223007 -2.59516588279 1.5000000995 5.0000000995 0.0883494486642" lengthrange="0.185892 0.207535" name="perbrev_r" tendon="perbrev_r_tendon" gaintype="compliant_mtu" />
        <general biasprm="0.816281 1.3032 993.42 1 0.530617 3.45831 10 1.14971 1.4 0" class="muscle" gainprm="1039.09239026 0.0474263163806 0.325041068924 10.0000000433 0.66315863897 -2.32450992558 1.50000004281 5.00000004301 0.0695636168977" lengthrange="0.373688 0.398423" name="perlong_r" tendon="perlong_r_tendon" gaintype="compliant_mtu" />
        <general biasprm="0.1 1.8 819.319 1 0.1 3.5 10 1.62632 1.4 0" class="muscle" gainprm="991.518466862 0.0251524827515 0.113299320733 10.0000001 0.646671564467 -1.94439424824 1.5000001 5.0000001 0.0639611535604" lengthrange="0.0953594 0.167006" name="piri_r" tendon="piri_r_tendon" gaintype="compliant_mtu" />
        <general biasprm="0.497633 1.12953 1385.41 1 0.0134813 1.52019 10 1.47869 1.4 0" class="muscle" gainprm="1303.14629595 0.0993664297924 0.0945675505269 10 0.538578213454 -1.35048413521 1.5 5 0.143472943045" lengthrange="0.157716 0.231585" name="psoas_r" tendon="psoas_r_tendon" gaintype="compliant_mtu" />
        <general biasprm="0.1 1.8 2211.57 1 0.1 3.5 10 1.78166 1.4 0" class="muscle" gainprm="2015.70334173 0.0752521143092 0.440192622188 10 0.89515470619 -6.37534707262 1.5 5 0.0587108050481" lengthrange="0.423402 0.713662" name="recfem_r" tendon="recfem_r_tendon" gaintype="compliant_mtu" />
        <general biasprm="0.602155 1.16939 245.514 1 0 3.5 10 0.806615 1.4 0" class="muscle" gainprm="241.25557907 0.381488074872 0.122538873531 10 0.65710464037 -2.48555959973 1.5 5 0.0372449052106" lengthrange="0.366668 0.595265" name="sart_r" tendon="sart_r_tendon" gaintype="compliant_mtu" />
        <general biasprm="0.1 1.8 2249.55 1 0.0886069 3.5 10 1.07055 1.4 0" class="muscle" gainprm="2027.66075822 0.0731115451875 0.323594347192 10.0000000852 0.773557333671 -3.899956505 1.50000008521 5.00000008521 0.0986281128737" lengthrange="0.299644 0.504801" name="semimem_r" tendon="semimem_r_tendon" gaintype="compliant_mtu" />
        <general biasprm="0.389685 1.68623 583.121 1 0 3.5 10 1.57478 1.4 0" class="muscle" gainprm="540.02316562 0.164059971202 0.234905332588 10.0000000596 0.768032918824 -3.48975756214 1.50000005932 5.00000005942 0.14766857914" lengthrange="0.322408 0.572642" name="semiten_r" tendon="semiten_r_tendon" gaintype="compliant_mtu" />
        <general biasprm="0.360484 1.51929 5322.19 1 0.142043 3.39743 10 1.5467 1.4 0" class="muscle" gainprm="5449.32372796 0.0391707520367 0.269882688299 10.0000000005 0.755791669325 -3.26155601704 1.5000000005 5.0000000005 0.0918860623755" lengthrange="0.292617 0.343605" name="soleus_r" tendon="soleus_r_tendon" gaintype="compliant_mtu" />
        <general biasprm="0.1 1.46235 265.756 1 0.1 3.28179 10 1.33831 1.4 0" class="muscle" gainprm="392.592265875 0.0847032319227 0.427825442465 10.0000001 0.666448536059 -3.63615398051 1.5000001 5.0000001 0.0803088782721" lengthrange="0.373121 0.588421" name="tfl_r" tendon="tfl_r_tendon" gaintype="compliant_mtu" />
        <general biasprm="0.601012 1.38869 1152.86 1 0.241731 2.70077 10 1.34727 1.4 0" class="muscle" gainprm="1147.51870166 0.059368566131 0.233269689463 10 0.765284421192 -4.04693123501 1.5 5 0.0926679794392" lengthrange="0.28151 0.335308" name="tibant_r" tendon="tibant_r_tendon" gaintype="compliant_mtu" />
        <general biasprm="0.627194 1.23083 1434.86 1 0.363757 2.9639 10 1.34057 1.4 0" class="muscle" gainprm="1608.79694489 0.0370437877064 0.277510752908 10.0000000374 0.659711246598 -2.38123674436 1.50000003685 5.00000003707 0.0490297119618" lengthrange="0.304488 0.327305" name="tibpost_r" tendon="tibpost_r_tendon" gaintype="compliant_mtu" />
        <general biasprm="0.804197 1.8 1759.46 1 0.408078 3.5 10 0.993224 1.4 0" class="muscle" gainprm="1617.5918207 0.104634641469 0.19741542503 10 0.74849290483 -4.25582878436 1.5 5 0.106481362351" lengthrange="0.282067 0.454352" name="vasint_r" tendon="vasint_r_tendon" gaintype="compliant_mtu" />
        <general biasprm="0.754438 1.8 5318.07 1 0.3408 3.5 10 2 1.4 0" class="muscle" gainprm="4641.05988746 0.110507544776 0.215802290749 10.000000011 0.752376169378 -3.67758148787 1.50000001105 5.00000001105 0.0362347373417" lengthrange="0.295592 0.476057" name="vaslat_r" tendon="vaslat_r_tendon" gaintype="compliant_mtu" />
        <general biasprm="1.14989 1.61299 2423.69 1 0.682608 3.5 10 1.40617 1.4 0" class="muscle" gainprm="2375.34486029 0.102100206847 0.204060030474 10.0000000004 0.737887734771 -2.97098601831 1.50000000006 5.00000000021 0.037225117132" lengthrange="0.311214 0.356041" name="vasmed_r" tendon="vasmed_r_tendon" gaintype="compliant_mtu" />
        <general biasprm="0.381903 1.46199 602.897 1 0.0683724 3.07879 10 1.3614 1.4 0" class="muscle" gainprm="631.360531044 0.097193502152 0.0348080472906 10.000000001 0.567054318052 -1.75468309422 1.50000000015 5.0000000005 0.037517457159" lengthrange="0.0748245 0.186181" name="addbrev_l" tendon="addbrev_l_tendon" gaintype="compliant_mtu" />
        <general biasprm="0.361607 1.56839 881.343 1 0.125586 3.49915 10 1.54262 1.4 0" class="muscle" gainprm="916.800496497 0.108042356079 0.131738967184 10.000000001 0.559915042633 -2.99538355964 1.50000000015 5.0000000005 0.0399919616931" lengthrange="0.170925 0.301499" name="addlong_l" tendon="addlong_l_tendon" gaintype="compliant_mtu" />
        <general biasprm="0.647072 1.32551 581.265 1 0.0381507 2.10964 10 1.23765 1.4 0" class="muscle" gainprm="556.161980009 0.165223108449 0.0859723648428 10.000000052 0.682471608034 -2.51439918445 1.50000005155 5.00000005172 0.036546794918" lengthrange="0.202042 0.322261" name="addmagDist_l" tendon="addmagDist_l_tendon" gaintype="compliant_mtu" />
        <general biasprm="0.662907 1.54717 566.285 1 0.139716 3.49861 10 1.14344 1.4 0" class="muscle" gainprm="560.113678756 0.13742241467 0.205725823411 10.0000000995 0.682123083771 -2.84154704207 1.5000000995 5.0000000995 0.132859400081" lengthrange="0.319889 0.458011" name="addmagIsch_l" tendon="addmagIsch_l_tendon" gaintype="compliant_mtu" />
        <general biasprm="0.477896 1.27927 578.677 1 0.0208952 2.02504 10 0.870476 1.4 0" class="muscle" gainprm="555.695452119 0.127774760301 0.0458046062033 10.0000000006 0.684228487441 -2.52165537951 1.50000000009 5.00000000029 0.0363339286248" lengthrange="0.112434 0.222784" name="addmagMid_l" tendon="addmagMid_l_tendon" gaintype="compliant_mtu" />
        <general biasprm="0.1628 1.1024 568.695 1 0 2.16935 10 1.06805 1.4 0" class="muscle" gainprm="542.213173705 0.089760565717 0.0383224967735 10.0000000454 0.74061126063 -2.58233859967 1.50000004497 5.00000004516 0.206138261913" lengthrange="0.0575158 0.156738" name="addmagProx_l" tendon="addmagProx_l_tendon" gaintype="compliant_mtu" />
        <general biasprm="0.1 1.8 1327.75 1 0.05 3.5 10 1.75486 1.4 0" class="muscle" gainprm="1230.45123603 0.087424245875 0.320979149479 10.0000001 0.732585198375 -3.85239006352 1.5000001 5.0000001 0.0911562254984" lengthrange="0.311093 0.518283" name="bflh_l" tendon="bflh_l_tendon" gaintype="compliant_mtu" />
        <general biasprm="0.406318 1.19782 556.777 1 0 3.14497 10 0.922935 1.4 0" class="muscle" gainprm="506.27055531 0.0937556165498 0.100527108051 10.0000001 0.732685732362 -2.8530150457 1.5000001 5.0000001 0.157323783368" lengthrange="0.150634 0.237936" name="bfsh_l" tendon="bfsh_l_tendon" gaintype="compliant_mtu" />
        <general biasprm="0.620259 1.40474 545.598 1 0.313821 3.47851 10 1.79438 1.4 0" class="muscle" gainprm="559.614385207 0.0617745094574 0.357547003967 10.0000000005 0.730624602016 -3.58420125982 1.5000000005 5.0000000005 0.0854096547223" lengthrange="0.411859 0.466224" name="edl_l" tendon="edl_l_tendon" gaintype="compliant_mtu" />
        <general biasprm="0.696495 1.41066 266.688 1 0.343273 3.26938 10 1.3865 1.4 0" class="muscle" gainprm="265.844496682 0.067987168893 0.316808734368 10.0000000995 0.713538551072 -3.43849524084 1.5000000995 5.0000000995 0.0818235539232" lengthrange="0.378893 0.432312" name="ehl_l" tendon="ehl_l_tendon" gaintype="compliant_mtu" />
        <general biasprm="0.5985 1.22918 331.887 1 0.352282 3.35018 10 1.69894 1.4 0" class="muscle" gainprm="391.882926639 0.0402059383655 0.371415046347 10.0000001 0.676348245751 -2.73102756238 1.5000001 5.0000001 0.0687195816217" lengthrange="0.405466 0.433594" name="fdl_l" tendon="fdl_l_tendon" gaintype="compliant_mtu" />
        <general biasprm="0.562475 1.18745 746.517 1 0.288301 3.5 10 0.896858 1.4 0" class="muscle" gainprm="832.577258483 0.0487431918584 0.343592607774 10 0.669825002137 -2.76552576086 1.5 5 0.0779805938534" lengthrange="0.383982 0.416918" name="fhl_l" tendon="fhl_l_tendon" gaintype="compliant_mtu" />
        <general biasprm="0.1 1.49069 1324.37 1 0.05 3.5 10 1.93411 1.4 0" class="muscle" gainprm="1516.19818422 0.0675881325746 0.369999699057 10 0.62795302995 -1.55140593381 1.5 5 0.0610440482055" lengthrange="0.366291 0.463723" name="gaslat_l" tendon="gaslat_l_tendon" gaintype="compliant_mtu" />
        <general biasprm="0.1 1.45 2245.47 1 0.0869909 3.46941 10 1.38125 1.4 0" class="muscle" gainprm="2852.5615188 0.0574614775061 0.384356120709 10.0000000516 0.596452113604 -2.42165751997 1.50000005116 5.00000005133 0.0394390444885" lengthrange="0.371968 0.472667" name="gasmed_l" tendon="gasmed_l_tendon" gaintype="compliant_mtu" />
        <general biasprm="0.680894 1.34594 1272.23 1 0 2.05861 10 1.422 1.4 0" class="muscle" gainprm="859.41192231 0.124950024379 0.0829350003361 10.0000000076 0.739059147845 -2.29745652698 1.5000000076 5.0000000076 0.162582312842" lengthrange="0.148932 0.246694" name="glmax1_l" tendon="glmax1_l_tendon" gaintype="compliant_mtu" />
        <general biasprm="0.684001 1.42041 1308.55 1 0.000794702 3.38516 10 0.806346 1.4 0" class="muscle" gainprm="1213.38892283 0.133878707032 0.103738915445 10.000000063 0.737550549812 -2.24193529383 1.50000006295 5.00000006299 0.137254076028" lengthrange="0.175275 0.290891" name="glmax2_l" tendon="glmax2_l_tendon" gaintype="compliant_mtu" />
        <general biasprm="1.36664 1.8 929.762 1 0.322928 3.5 10 1.93452 1.4 0" class="muscle" gainprm="812.119706011 0.141950052364 0.0978628790291 10.0000000578 0.754487995245 -2.39823389798 1.50000005779 5.00000005779 0.130815916507" lengthrange="0.297946 0.474778" name="glmax3_l" tendon="glmax3_l_tendon" gaintype="compliant_mtu" />
        <general biasprm="0.103084 1.4555 1018.93 1 4.15271e-06 3.48299 10 1.46926 1.4 0" class="muscle" gainprm="973.355928205 0.0650250091274 0.055575000039 10 0.730599854042 -2.432496862 1.5 5 0.162629781677" lengthrange="0.063342 0.162068" name="glmed1_l" tendon="glmed1_l_tendon" gaintype="compliant_mtu" />
        <general biasprm="0.147694 1.46079 716.963 1 0 3.39296 10 1.74572 1.4 0" class="muscle" gainprm="698.127045045 0.0714320564733 0.0736093643994 10.0000000395 0.705261787181 -1.84479407161 1.50000003948 5.00000003948 0.167207243316" lengthrange="0.0760304 0.171887" name="glmed2_l" tendon="glmed2_l_tendon" gaintype="compliant_mtu" />
        <general biasprm="0.125877 1.51901 826.643 1 0.000637198 3.49115 10 1.65163 1.4 0" class="muscle" gainprm="812.15087769 0.0664156946279 0.0470613845276 10.0000000487 0.668720871356 -1.53426422178 1.50000004869 5.00000004869 0.239571795188" lengthrange="0.0544219 0.156121" name="glmed3_l" tendon="glmed3_l_tendon" gaintype="compliant_mtu" />
        <general biasprm="0.1 1.44635 357.562 1 0.0602573 3.02127 10 1.3101 1.4 0" class="muscle" gainprm="350.282106104 0.0758592248494 0.0190059710581 10 0.678571299824 -2.52755874365 1.5 5 0.0363773490968" lengthrange="0.0229136 0.11449" name="glmin1_l" tendon="glmin1_l_tendon" gaintype="compliant_mtu" />
        <general biasprm="0.1 1.60052 391.417 1 0.1 3.5 10 1.19315 1.4 0" class="muscle" gainprm="374.169384518 0.0646083117723 0.0316051917777 10.0000000324 0.66701794083 -2.65673818037 1.50000003184 5.00000003208 0.0369183080949" lengthrange="0.0298796 0.115728" name="glmin2_l" tendon="glmin2_l_tendon" gaintype="compliant_mtu" />
        <general biasprm="0.1 1.8 389.612 1 0.0939983 3.5 10 1.15519 1.4 0" class="muscle" gainprm="426.354064508 0.0315612898765 0.0461500888966 10.0000000995 0.661510841193 -2.66543882264 1.5000000995 5.0000000995 0.10281777196" lengthrange="0.0345943 0.11994" name="glmin3_l" tendon="glmin3_l_tendon" gaintype="compliant_mtu" />
        <general biasprm="0.652458 1.62414 280.263 1 0 3.5 10 1.68108 1.4 0" class="muscle" gainprm="272.783280789 0.200310838306 0.166346137838 10.0000000995 0.673032658858 -2.21286958079 1.5000000995 5.0000000995 0.196976636585" lengthrange="0.320644 0.541993" name="grac_l" tendon="grac_l_tendon" gaintype="compliant_mtu" />
        <general biasprm="0.24456 1.23695 974.831 1 0 1.8511 10 1.69465 1.4 0" class="muscle" gainprm="1023.22974197 0.110522663509 0.0996167649857 10 0.475237427473 -0.454363166869 1.5 5 0.0622475705423" lengthrange="0.122191 0.22798" name="iliacus_l" tendon="iliacus_l_tendon" gaintype="compliant_mtu" />
        <general biasprm="0.845027 1.32175 496.73 1 0.467464 3.06759 10 1.61433 1.4 0" class="muscle" gainprm="485.49059667 0.0411863690606 0.14264109552 10.0000000995 0.667285223007 -2.59516588279 1.5000000995 5.0000000995 0.0883494486642" lengthrange="0.185892 0.207535" name="perbrev_l" tendon="perbrev_l_tendon" gaintype="compliant_mtu" />
        <general biasprm="0.816281 1.3032 997.426 1 0.540714 3.40374 10 1.41808 1.4 0" class="muscle" gainprm="1039.09239026 0.0474263163806 0.325041068924 10.0000000433 0.66315863897 -2.32450992558 1.50000004281 5.00000004301 0.0695636168977" lengthrange="0.373688 0.398423" name="perlong_l" tendon="perlong_l_tendon" gaintype="compliant_mtu" />
        <general biasprm="0.1 1.8 822.575 1 0.0713008 3.5 10 0.992879 1.4 0" class="muscle" gainprm="991.518466862 0.0251524827515 0.113299320733 10.0000001 0.646671564467 -1.94439424824 1.5000001 5.0000001 0.0639611535604" lengthrange="0.0953594 0.167006" name="piri_l" tendon="piri_l_tendon" gaintype="compliant_mtu" />
        <general biasprm="0.497633 1.12953 1366.97 1 0.0118191 1.73378 10 1.03401 1.4 0" class="muscle" gainprm="1303.14629595 0.0993664297924 0.0945675505269 10 0.538578213454 -1.35048413521 1.5 5 0.143472943045" lengthrange="0.157716 0.231585" name="psoas_l" tendon="psoas_l_tendon" gaintype="compliant_mtu" />
        <general biasprm="0.1 1.8 2205.94 1 0.1 3.5 10 1.95607 1.4 0" class="muscle" gainprm="2015.70334173 0.0752521143092 0.440192622188 10 0.89515470619 -6.37534707262 1.5 5 0.0587108050481" lengthrange="0.423402 0.713662" name="recfem_l" tendon="recfem_l_tendon" gaintype="compliant_mtu" />
        <general biasprm="0.602155 1.16939 248.635 1 0.00170046 1.82656 10 1.79532 1.4 0" class="muscle" gainprm="241.25557907 0.381488074872 0.122538873531 10 0.65710464037 -2.48555959973 1.5 5 0.0372449052106" lengthrange="0.366668 0.595265" name="sart_l" tendon="sart_l_tendon" gaintype="compliant_mtu" />
        <general biasprm="0.1 1.8 2196.22 1 0.05 3.49955 10 1.30483 1.4 0" class="muscle" gainprm="2027.66075822 0.0731115451875 0.323594347192 10.0000000852 0.773557333671 -3.899956505 1.50000008521 5.00000008521 0.0986281128737" lengthrange="0.299644 0.504801" name="semimem_l" tendon="semimem_l_tendon" gaintype="compliant_mtu" />
        <general biasprm="0.389685 1.68623 579.776 1 0.0312812 3.5 10 1.94751 1.4 0" class="muscle" gainprm="540.02316562 0.164059971202 0.234905332588 10.0000000596 0.768032918824 -3.48975756214 1.50000005932 5.00000005942 0.14766857914" lengthrange="0.322408 0.572642" name="semiten_l" tendon="semiten_l_tendon" gaintype="compliant_mtu" />
        <general biasprm="0.360484 1.51929 5284.56 1 0.130611 3.5 10 1.35441 1.4 0" class="muscle" gainprm="5449.32372796 0.0391707520367 0.269882688299 10.0000000005 0.755791669325 -3.26155601704 1.5000000005 5.0000000005 0.0918860623755" lengthrange="0.292617 0.343605" name="soleus_l" tendon="soleus_l_tendon" gaintype="compliant_mtu" />
        <general biasprm="0.1 1.46235 262.053 1 0.1 3.49308 10 1.13577 1.4 0" class="muscle" gainprm="392.592265875 0.0847032319227 0.427825442465 10.0000001 0.666448536059 -3.63615398051 1.5000001 5.0000001 0.0803088782721" lengthrange="0.373121 0.588421" name="tfl_l" tendon="tfl_l_tendon" gaintype="compliant_mtu" />
        <general biasprm="0.601012 1.38869 1143.45 1 0.235755 3.05219 10 1.36022 1.4 0" class="muscle" gainprm="1147.51870166 0.059368566131 0.233269689463 10 0.765284421192 -4.04693123501 1.5 5 0.0926679794392" lengthrange="0.28151 0.335308" name="tibant_l" tendon="tibant_l_tendon" gaintype="compliant_mtu" />
        <general biasprm="0.627194 1.23083 1429.97 1 0.35657 3.14947 10 1.76838 1.4 0" class="muscle" gainprm="1608.79694489 0.0370437877064 0.277510752908 10.0000000374 0.659711246598 -2.38123674436 1.50000003685 5.00000003707 0.0490297119618" lengthrange="0.304488 0.327305" name="tibpost_l" tendon="tibpost_l_tendon" gaintype="compliant_mtu" />
        <general biasprm="0.804197 1.8 1759.59 1 0.403463 3.5 10 1.60134 1.4 0" class="muscle" gainprm="1617.5918207 0.104634641469 0.19741542503 10 0.74849290483 -4.25582878436 1.5 5 0.106481362351" lengthrange="0.282067 0.454352" name="vasint_l" tendon="vasint_l_tendon" gaintype="compliant_mtu" />
        <general biasprm="0.754438 1.8 5322.59 1 0.340667 3.5 10 1.80773 1.4 0" class="muscle" gainprm="4641.05988746 0.110507544776 0.215802290749 10.000000011 0.752376169378 -3.67758148787 1.50000001105 5.00000001105 0.0362347373417" lengthrange="0.295592 0.476057" name="vaslat_l" tendon="vaslat_l_tendon" gaintype="compliant_mtu" />
        <general biasprm="1.14989 1.61299 2422.17 1 0.412194 3.49301 10 1.4918 1.4 0" class="muscle" gainprm="2375.34486029 0.102100206847 0.204060030474 10.0000000004 0.737887734771 -2.97098601831 1.50000000006 5.00000000021 0.037225117132" lengthrange="0.311214 0.356041" name="vasmed_l" tendon="vasmed_l_tendon" gaintype="compliant_mtu" />
    </actuator>
</mujocoinclude>